outliers_detect/__init__.py
outliers_detect/core.py
outliers_detect-0.1.0.dist-info/METADATA
outliers_detect-0.1.0.dist-info/WHEEL
outliers_detect-0.1.0.dist-info/RECORD
