Metadata-Version: 2.4
Name: outliers_detect
Version: 0.1.0
Summary: Uma biblioteca para detecção de outliers em embeddings
Project-URL: Homepage, https://github.com/seu-usuario/outliers_detect
Project-URL: Bug Tracker, https://github.com/seu-usuario/outliers_detect/issues
Author-email: Seu Nome <seu.email@exemplo.com>
Classifier: License :: OSI Approved :: MIT License
Classifier: Operating System :: OS Independent
Classifier: Programming Language :: Python :: 3
Requires-Python: >=3.8
Requires-Dist: matplotlib>=3.4.0
Requires-Dist: numpy>=1.20.0
Requires-Dist: pandas>=1.3.0
Requires-Dist: scikit-learn>=1.0.0
Requires-Dist: scipy>=1.7.0
Provides-Extra: dev
Requires-Dist: pytest-cov>=3.0.0; extra == 'dev'
Requires-Dist: pytest>=7.0.0; extra == 'dev'
